setup.py
odoo/addons/widget_mail_composer_email_to/CHANGELOG.md
odoo/addons/widget_mail_composer_email_to/README.rst
odoo/addons/widget_mail_composer_email_to/__init__.py
odoo/addons/widget_mail_composer_email_to/__manifest__.py
odoo/addons/widget_mail_composer_email_to/i18n/ca_ES.po
odoo/addons/widget_mail_composer_email_to/i18n/es.po
odoo/addons/widget_mail_composer_email_to/models/__init__.py
odoo/addons/widget_mail_composer_email_to/models/helpdesk_ticket.py
odoo/addons/widget_mail_composer_email_to/models/res_company.py
odoo/addons/widget_mail_composer_email_to/models/res_config_settings.py
odoo/addons/widget_mail_composer_email_to/static/description/icon.png
odoo/addons/widget_mail_composer_email_to/static/src/css/mail_compose_message_email_to.css
odoo/addons/widget_mail_composer_email_to/static/src/js/mail_compose_message_email_to.js
odoo/addons/widget_mail_composer_email_to/static/src/xml/templates.xml
odoo/addons/widget_mail_composer_email_to/views/res_config_settings.xml
odoo/addons/widget_mail_composer_email_to/wizards/mail_compose_message_view.xml
odoo_addon_widget_mail_composer_email_to.egg-info/PKG-INFO
odoo_addon_widget_mail_composer_email_to.egg-info/SOURCES.txt
odoo_addon_widget_mail_composer_email_to.egg-info/dependency_links.txt
odoo_addon_widget_mail_composer_email_to.egg-info/not-zip-safe
odoo_addon_widget_mail_composer_email_to.egg-info/requires.txt
odoo_addon_widget_mail_composer_email_to.egg-info/top_level.txt